dotsi.py
dotsi-0.0.3.dist-info/LICENSE.txt
dotsi-0.0.3.dist-info/WHEEL
dotsi-0.0.3.dist-info/METADATA
dotsi-0.0.3.dist-info/RECORD
