Metadata-Version: 2.1
Name: dotsi
Version: 0.0.3
Summary: Dotsi: Dot-accessible, update-aware Python dicts (& lists).
Home-page: https://github.com/polydojo/dotsi
License: UNKNOWN
Author: Polydojo, Inc.
Author-email: 8079593+sumukhbarve@users.noreply.github.com
Classifier: License :: OSI Approved :: MIT License
